pytest_kubernetes/__init__.py
pytest_kubernetes/kubectl.py
pytest_kubernetes/options.py
pytest_kubernetes/plugin.py
pytest_kubernetes/portforwarding.py
pytest_kubernetes/providers/__init__.py
pytest_kubernetes/providers/base.py
pytest_kubernetes/providers/external.py
pytest_kubernetes/providers/k3d.py
pytest_kubernetes/providers/kind.py
pytest_kubernetes/providers/minikube.py
pytest_kubernetes-0.7.2.dist-info/METADATA
pytest_kubernetes-0.7.2.dist-info/WHEEL
pytest_kubernetes-0.7.2.dist-info/entry_points.txt
pytest_kubernetes-0.7.2.dist-info/licenses/LICENSE
pytest_kubernetes-0.7.2.dist-info/RECORD
