Metadata-Version: 2.4
Name: pytest-kubernetes
Version: 0.7.2
Summary: 
License-File: LICENSE
Author: Michael Schilonka
Author-email: michael@blueshoe.io
Requires-Python: >=3.11.7,<4.0.0
Classifier: Framework :: Pytest
Classifier: Programming Language :: Python :: 3
Classifier: Programming Language :: Python :: 3.12
Classifier: Programming Language :: Python :: 3.13
Classifier: Programming Language :: Python :: 3.14
Classifier: Programming Language :: Python :: 3.10
Classifier: Programming Language :: Python :: 3.8
Classifier: Programming Language :: Python :: 3.9
Classifier: Topic :: Software Development :: Testing
Requires-Dist: pytest (>=8.3.0,<9.0.0)
Requires-Dist: pyyaml (>=6.0,<7.0)
Project-URL: Repository, https://github.com/Blueshoe/pytest-kubernetes
